stretchy/__init__.py
stretchy/__init__.pyi
stretchy/abc.py
stretchy/abc.pyi
stretchy/array1d.py
stretchy/array1d.pyi
stretchy/arraynd.py
stretchy/arraynd.pyi
stretchy/format.py
stretchy/format.pyi
stretchy/py.typed
stretchy-1.1b1.dist-info/METADATA
stretchy-1.1b1.dist-info/WHEEL
stretchy-1.1b1.dist-info/licenses/LICENSE
stretchy-1.1b1.dist-info/RECORD
