Metadata-Version: 2.1
Name: stretchy
Version: 1.1b1
Summary: One- and multi-dimensional containers that grow automatically in all directions
Project-URL: Homepage, https://github.com/fercsi/pylib-stretchy
Project-URL: Bug Tracker, https://github.com/fercsi/pylib-stretchy/issues
Author-email: Ferenc Vajda <ferenc.vajda@gmail.com>
License-File: LICENSE
Classifier: License :: OSI Approved :: MIT License
Classifier: Operating System :: OS Independent
Classifier: Programming Language :: Python :: 3
Requires-Python: >=3.10
